list2excel/__init__.py
list2excel/admin.py
list2excel/constants.py
list2excel/core.py
list2excel/helpers.py
list2excel/models.py
list2excel/settings.py
list2excel/urls.py
list2excel/views.py
list2excel-0.5.6.dist-info/DESCRIPTION.rst
list2excel-0.5.6.dist-info/METADATA
list2excel-0.5.6.dist-info/RECORD
list2excel-0.5.6.dist-info/WHEEL
list2excel-0.5.6.dist-info/metadata.json
list2excel-0.5.6.dist-info/top_level.txt
