Metadata-Version: 2.0
Name: list2excel
Version: 0.5.6
Summary: Django XLS export made easy
Home-page: http://bitbucket.org/brente/list2excel/
Author: Stefano Brentegani
Author-email: sbrentegani@gmail.com
License: MIT License
Download-URL: http://bitbucket.org/brente/list2excel/downloads/list2excel-0.5.6.tar.gz
Platform: UNKNOWN
Classifier: Development Status :: 4 - Beta
Classifier: Environment :: Web Environment
Classifier: Framework :: Django
Classifier: Intended Audience :: Developers
Classifier: License :: OSI Approved :: MIT License
Classifier: Operating System :: OS Independent
Classifier: Programming Language :: Python
Classifier: Topic :: Software Development :: Libraries :: Python Modules
Requires-Dist: Django (<1.9,>=1.4)
Requires-Dist: xlwt (>=0.7.4)
